{
  "deployment_id": "20260127_125348",
  "timestamp": "2026-01-27T12:53:48.063398",
  "changes": {
    "new_tables": [
      "payment_region_config",
      "payment_transactions",
      "fx_rate_history",
      "payment_whitelist",
      "payment_api_call_logs",
      "conversion_fee_history"
    ],
    "new_columns": [],
    "modified_columns": [],
    "new_tables_data": [
      {
        "table": "payment_region_config",
        "row_count": 10
      },
      {
        "table": "payment_transactions",
        "row_count": 2
      },
      {
        "table": "fx_rate_history",
        "row_count": 2
      },
      {
        "table": "payment_whitelist",
        "row_count": 2
      }
    ],
    "table_data_diff": [
      {
        "table": "homepage_contents",
        "diff_count": 9
      },
      {
        "table": "payment_configs",
        "diff_count": 4
      }
    ]
  }
}