{
  "十三宫位规则": [
    {
      "rule_type": "gongwei",
      "position": "天中",
      "position_code": "tianchong",
      "conditions": {
        "region": "forehead_top",
        "features": ["饱满", "平润", "光洁"]
      },
      "interpretations": [
        {
          "feature": "饱满明润",
          "interpretation": "早年得志，15-16岁学业顺利，智慧聪颖",
          "category": "事业"
        },
        {
          "feature": "凹陷暗沉",
          "interpretation": "早年不利，家境一般，需靠自己奋斗",
          "category": "事业"
        }
      ],
      "priority": 80
    },
    {
      "rule_type": "gongwei",
      "position": "天庭",
      "position_code": "tinting",
      "conditions": {
        "region": "forehead_upper",
        "features": ["宽阔", "饱满", "光泽"]
      },
      "interpretations": [
        {
          "feature": "宽阔饱满",
          "interpretation": "聪明智慧，17-18岁学业有成，家庭背景好",
          "category": "性格"
        },
        {
          "feature": "窄小凹陷",
          "interpretation": "少年辛苦，需后天努力，家境普通",
          "category": "性格"
        }
      ],
      "priority": 85
    },
    {
      "rule_type": "gongwei",
      "position": "司空",
      "position_code": "sikong",
      "conditions": {
        "region": "forehead_middle",
        "features": ["平满", "光润"]
      },
      "interpretations": [
        {
          "feature": "平满光润",
          "interpretation": "19-20岁运势佳，求学顺利，有贵人相助",
          "category": "事业"
        },
        {
          "feature": "有疤痕或凹陷",
          "interpretation": "此年运势波折，需谨慎行事",
          "category": "事业"
        }
      ],
      "priority": 75
    },
    {
      "rule_type": "gongwei",
      "position": "中正",
      "position_code": "zhongzheng",
      "conditions": {
        "region": "forehead_lower",
        "features": ["端正", "平满"]
      },
      "interpretations": [
        {
          "feature": "端正平满",
          "interpretation": "21-22岁事业起步顺利，为人正直",
          "category": "性格"
        }
      ],
      "priority": 75
    },
    {
      "rule_type": "gongwei",
      "position": "印堂",
      "position_code": "yintang",
      "conditions": {
        "region": "between_eyebrows",
        "features": ["开阔", "平满", "明润", "颜色"]
      },
      "interpretations": [
        {
          "feature": "开阔平满",
          "interpretation": "命宫开阔，28岁运势极佳，一生顺遂，心胸宽广",
          "category": "综合"
        },
        {
          "feature": "狭窄或有竖纹",
          "interpretation": "心胸较窄，易钻牛角尖，运势起伏",
          "category": "性格"
        },
        {
          "feature": "印堂发黑",
          "interpretation": "近期运势不佳，需注意健康和安全",
          "category": "健康"
        },
        {
          "feature": "印堂红润",
          "interpretation": "近期有喜事，运势上扬",
          "category": "财运"
        }
      ],
      "priority": 100
    },
    {
      "rule_type": "gongwei",
      "position": "山根",
      "position_code": "shangen",
      "conditions": {
        "region": "nose_bridge_root",
        "features": ["高低", "宽窄", "有无断节"]
      },
      "interpretations": [
        {
          "feature": "山根高起",
          "interpretation": "41岁运势佳，身体健康，事业稳固",
          "category": "健康"
        },
        {
          "feature": "山根低陷",
          "interpretation": "41岁需注意健康，运势有波折",
          "category": "健康"
        },
        {
          "feature": "山根有横纹",
          "interpretation": "中年易有变动，需谨慎理财",
          "category": "财运"
        }
      ],
      "priority": 80
    },
    {
      "rule_type": "gongwei",
      "position": "年上寿上",
      "position_code": "nianshang_shoushang",
      "conditions": {
        "region": "nose_bridge_middle",
        "features": ["挺直", "有无节"]
      },
      "interpretations": [
        {
          "feature": "挺直无节",
          "interpretation": "44-45岁运势平稳，身体健康",
          "category": "健康"
        },
        {
          "feature": "有节或弯曲",
          "interpretation": "中年运势波折，需注意健康",
          "category": "健康"
        }
      ],
      "priority": 70
    },
    {
      "rule_type": "gongwei",
      "position": "准头",
      "position_code": "zhuntou",
      "conditions": {
        "region": "nose_tip",
        "features": ["大小", "形状", "肉质", "颜色"]
      },
      "interpretations": [
        {
          "feature": "鼻头圆润有肉",
          "interpretation": "48-50岁财运极佳，一生财运亨通，善于聚财",
          "category": "财运"
        },
        {
          "feature": "鼻头尖薄",
          "interpretation": "财运平平，不易聚财，需节俭持家",
          "category": "财运"
        },
        {
          "feature": "鼻头有痣",
          "interpretation": "财运有波折，注意破财",
          "category": "财运"
        },
        {
          "feature": "鼻头红润",
          "interpretation": "近期财运佳，有进财机会",
          "category": "财运"
        }
      ],
      "priority": 95
    },
    {
      "rule_type": "gongwei",
      "position": "人中",
      "position_code": "renzhong",
      "conditions": {
        "region": "philtrum",
        "features": ["深浅", "长短", "宽窄"]
      },
      "interpretations": [
        {
          "feature": "人中深长",
          "interpretation": "51岁运势佳，子女孝顺，长寿健康",
          "category": "健康"
        },
        {
          "feature": "人中短浅",
          "interpretation": "子女缘薄，需注意生殖系统健康",
          "category": "健康"
        }
      ],
      "priority": 75
    },
    {
      "rule_type": "gongwei",
      "position": "水星",
      "position_code": "shuixing",
      "conditions": {
        "region": "mouth",
        "features": ["嘴型", "唇色", "大小"]
      },
      "interpretations": [
        {
          "feature": "嘴唇红润饱满",
          "interpretation": "60岁运势佳，口福好，晚年安康",
          "category": "健康"
        },
        {
          "feature": "嘴唇薄且色淡",
          "interpretation": "口才佳但情感波折，需注意脾胃",
          "category": "健康"
        }
      ],
      "priority": 70
    },
    {
      "rule_type": "gongwei",
      "position": "承浆",
      "position_code": "chengjiang",
      "conditions": {
        "region": "below_lower_lip",
        "features": ["饱满", "凹陷"]
      },
      "interpretations": [
        {
          "feature": "饱满有肉",
          "interpretation": "61岁运势平稳，子孙满堂",
          "category": "健康"
        }
      ],
      "priority": 65
    },
    {
      "rule_type": "gongwei",
      "position": "地阁",
      "position_code": "dige",
      "conditions": {
        "region": "chin",
        "features": ["饱满", "方圆", "双下巴"]
      },
      "interpretations": [
        {
          "feature": "地阁方圆饱满",
          "interpretation": "晚年运势极佳，福禄双全，子孙孝顺，有房有产",
          "category": "财运"
        },
        {
          "feature": "地阁尖削",
          "interpretation": "晚年孤独，需提前规划养老",
          "category": "财运"
        },
        {
          "feature": "双下巴",
          "interpretation": "晚年富贵，生活安逸",
          "category": "财运"
        }
      ],
      "priority": 85
    }
  ]
}

